__builtins__.pyi
_boot.pyi
_onewire.pyi
_uasyncio.pyi
array.pyi
binascii.pyi
collections.pyi
dht.pyi
ds18x20.pyi
errno.pyi
framebuf.pyi
gc.pyi
hashlib.pyi
heapq.pyi
io.pyi
json.pyi
logging.pyi
machine.pyi
math.pyi
micropython.pyi
onewire.pyi
os.pyi
random.pyi
samd.pyi
select.pyi
struct.pyi
sys.pyi
time.pyi
uarray.pyi
uasyncio/__init__.pyi
uasyncio/core.pyi
uasyncio/event.pyi
uasyncio/funcs.pyi
uasyncio/lock.pyi
uasyncio/stream.pyi
uasyncio/task.pyi
ubinascii.pyi
ucollections.pyi
uctypes.pyi
uerrno.pyi
uhashlib.pyi
uheapq.pyi
uio.pyi
ujson.pyi
umachine.pyi
uos.pyi
urandom.pyi
ure.pyi
uselect.pyi
ustruct.pyi
usys.pyi
utime.pyi
uzlib.pyi
zlib.pyi
micropython_samd_adafruit_feather_m4_express_stubs-1.20.0.post3.dist-info/LICENSE.md
micropython_samd_adafruit_feather_m4_express_stubs-1.20.0.post3.dist-info/METADATA
micropython_samd_adafruit_feather_m4_express_stubs-1.20.0.post3.dist-info/WHEEL
micropython_samd_adafruit_feather_m4_express_stubs-1.20.0.post3.dist-info/RECORD
