Metadata-Version: 2.1
Name: micropython-samd-adafruit_feather_m4_express-stubs
Version: 1.20.0.post3
Summary: MicroPython stubs
Home-page: https://github.com/josverl/micropython-stubs#micropython-stubs
License: MIT
Author: josverl
Author-email: josverl@users.noreply.github.com
Requires-Python: >=3.8,<4.0
Classifier: Development Status :: 4 - Beta
Classifier: License :: OSI Approved :: MIT License
Classifier: Operating System :: OS Independent
Classifier: Programming Language :: Python
Classifier: Programming Language :: Python :: 3
Classifier: Programming Language :: Python :: 3.8
Classifier: Programming Language :: Python :: 3.9
Classifier: Programming Language :: Python :: 3.10
Classifier: Programming Language :: Python :: 3.11
Classifier: Programming Language :: Python :: 3 :: Only
Classifier: Programming Language :: Python :: Implementation :: MicroPython
Classifier: Topic :: Software Development :: Build Tools
Classifier: Topic :: Text Editors :: Integrated Development Environments (IDE)
Classifier: Typing :: Typed
Requires-Dist: micropython-stdlib-stubs (>=0.9.0)
Project-URL: Documentation, https://micropython-stubs.readthedocs.io/
Project-URL: Repository, https://github.com/josverl/micropython-stubs
